<?xml version="1.0" encoding="iso-8859-1"?>
<Invoice xmlns:ds="http://www.w3.org/2000/09/xmldsig#" xmlns:qdt="urn:oasis:names:specification:ubl:schema:xsd:QualifiedDatatypes-2" xmlns:cbc="urn:oasis:names:specification:ubl:schema:xsd:CommonBasicComponents-2" xmlns:xsi="http://www.w3.org/2001/XMLSchema-instance" xmlns:udt="urn:un:unece:uncefact:data:specification:UnqualifiedDataTypesSchemaModule:2" xmlns:cac="urn:oasis:names:specification:ubl:schema:xsd:CommonAggregateComponents-2" xmlns:ext="urn:oasis:names:specification:ubl:schema:xsd:CommonExtensionComponents-2" xmlns:sac="urn:sunat:names:specification:ubl:peru:schema:xsd:SunatAggregateComponents-1" xmlns:ccts="urn:un:unece:uncefact:documentation:2" xmlns="urn:oasis:names:specification:ubl:schema:xsd:Invoice-2">
	<ext:UBLExtensions>
		<ext:UBLExtension>
			<ext:ExtensionContent><AdditionalInformationSLIN><Document><ID>20537924218-01-F001-00000009</ID></Document><Extra><ExLinea>1</ExLinea><ExDato><![CDATA[MIRAFLORES]]></ExDato><ExTipo></ExTipo></Extra><Extra><ExLinea>2</ExLinea><ExDato><![CDATA[F*F001-00000009]]></ExDato><ExTipo></ExTipo></Extra><Extra><ExLinea>3</ExLinea><ExDato><![CDATA[]]></ExDato><ExTipo></ExTipo></Extra><Extra><ExLinea>4</ExLinea><ExDato><![CDATA[12/01/2018]]></ExDato><ExTipo></ExTipo></Extra><Extra><ExLinea>5</ExLinea><ExDato><![CDATA[]]></ExDato><ExTipo></ExTipo></Extra><Extra><ExLinea>6</ExLinea><ExDato><![CDATA[001 - OFICINA]]></ExDato><ExTipo></ExTipo></Extra><Extra><ExLinea>7</ExLinea><ExDato><![CDATA[F30 - FACTURA DE 30 DIAS]]></ExDato><ExTipo></ExTipo></Extra><Extra><ExLinea>8</ExLinea><ExDato><![CDATA[]]></ExDato><ExTipo></ExTipo></Extra></AdditionalInformationSLIN></ext:ExtensionContent>
		</ext:UBLExtension>
		<ext:UBLExtension>
			<ext:ExtensionContent><sac:AdditionalInformation><sac:AdditionalMonetaryTotal><cbc:ID>1001</cbc:ID><cbc:PayableAmount currencyID="USD">22371.20</cbc:PayableAmount></sac:AdditionalMonetaryTotal><sac:AdditionalMonetaryTotal><cbc:ID>1002</cbc:ID><cbc:PayableAmount currencyID="USD">0.00</cbc:PayableAmount></sac:AdditionalMonetaryTotal><sac:AdditionalMonetaryTotal><cbc:ID>1003</cbc:ID><cbc:PayableAmount currencyID="USD">0.00</cbc:PayableAmount></sac:AdditionalMonetaryTotal><sac:AdditionalMonetaryTotal><cbc:ID>2003</cbc:ID><cbc:PayableAmount currencyID="USD">2639.80</cbc:PayableAmount><cbc:Percent>10.00</cbc:Percent></sac:AdditionalMonetaryTotal><sac:AdditionalProperty><cbc:ID>1000</cbc:ID><cbc:Value>VEINTISEIS MIL TRESCIENTOS NOVENTA Y OCHO Y 02/100 DOLARES AMERICANOS</cbc:Value></sac:AdditionalProperty><sac:AdditionalProperty><cbc:ID>3000</cbc:ID><cbc:Value>22</cbc:Value></sac:AdditionalProperty><sac:AdditionalProperty><cbc:ID>3001</cbc:ID><cbc:Value>00068275229</cbc:Value></sac:AdditionalProperty><sac:SUNATTransaction><cbc:ID>01</cbc:ID></sac:SUNATTransaction></sac:AdditionalInformation></ext:ExtensionContent>
		</ext:UBLExtension>
		<ext:UBLExtension>
			<ext:ExtensionContent />
		</ext:UBLExtension>
	</ext:UBLExtensions>
	<cbc:UBLVersionID>2.0</cbc:UBLVersionID>
	<cbc:CustomizationID>1.0</cbc:CustomizationID>
	<cbc:ID>F001-00000009</cbc:ID>
	<cbc:IssueDate>2017-12-13</cbc:IssueDate>
	<cbc:InvoiceTypeCode>01</cbc:InvoiceTypeCode>
	<cbc:DocumentCurrencyCode>USD</cbc:DocumentCurrencyCode>
	<cac:OrderReference>
		<cbc:ID>4700011383</cbc:ID>
	</cac:OrderReference>
	<cac:Signature>
		<cbc:ID>IDSign20537924218</cbc:ID>
		<cac:SignatoryParty>
			<cac:PartyIdentification>
				<cbc:ID>20537924218</cbc:ID>
			</cac:PartyIdentification>
			<cac:PartyName>
				<cbc:Name><![CDATA[GENERADORES GAMMA S.A.C]]></cbc:Name>
			</cac:PartyName>
		</cac:SignatoryParty>
		<cac:DigitalSignatureAttachment>
			<cac:ExternalReference>
				<cbc:URI>#signature20537924218</cbc:URI>
			</cac:ExternalReference>
		</cac:DigitalSignatureAttachment>
	</cac:Signature>
	<cac:AccountingSupplierParty>
		<cbc:CustomerAssignedAccountID>20537924218</cbc:CustomerAssignedAccountID>
		<cbc:AdditionalAccountID>6</cbc:AdditionalAccountID>
		<cac:Party>
			<cac:PartyName>
				<cbc:Name><![CDATA[GAMMA]]></cbc:Name>
			</cac:PartyName>
			<cac:PostalAddress>
				<cbc:ID>150119</cbc:ID>
				<cbc:StreetName><![CDATA[AV. LOS EUCALIPTOS #371 URB.STA.GENOVEVA - LURIN-LIMA-LIMA]]></cbc:StreetName>
				<cbc:CitySubdivisionName><![CDATA[-]]></cbc:CitySubdivisionName>
				<cbc:CityName><![CDATA[LIMA]]></cbc:CityName>
				<cbc:CountrySubentity><![CDATA[LIMA]]></cbc:CountrySubentity>
				<cbc:District><![CDATA[LURIN]]></cbc:District>
				<cac:Country>
					<cbc:IdentificationCode>PE</cbc:IdentificationCode>
				</cac:Country>
			</cac:PostalAddress>
			<cac:PartyLegalEntity>
				<cbc:RegistrationName><![CDATA[GENERADORES GAMMA S.A.C]]></cbc:RegistrationName>
			</cac:PartyLegalEntity>
		</cac:Party>
	</cac:AccountingSupplierParty>
	<cac:AccountingCustomerParty>
		<cbc:CustomerAssignedAccountID>20562692313</cbc:CustomerAssignedAccountID>
		<cbc:AdditionalAccountID>6</cbc:AdditionalAccountID>
		<cac:Party>
			<cac:PartyName>
				<cbc:Name><![CDATA[AZTECA COMUNICACIONES PERU S.A.C.]]></cbc:Name>
			</cac:PartyName>
			<cac:PostalAddress>
				<cbc:ID>150122</cbc:ID>
				<cbc:StreetName><![CDATA[AV. 28 DE JULIO NRO. 1011 URB. SAN ANTONIO (PISO 5) LIMA - LIMA - MIRAFLORES]]></cbc:StreetName>
				<cbc:CitySubdivisionName><![CDATA[-]]></cbc:CitySubdivisionName>
				<cbc:CityName><![CDATA[LIMA]]></cbc:CityName>
				<cbc:CountrySubentity><![CDATA[LIMA]]></cbc:CountrySubentity>
				<cbc:District><![CDATA[MIRAFLORES]]></cbc:District>
				<cac:Country>
					<cbc:IdentificationCode>PE</cbc:IdentificationCode>
				</cac:Country>
			</cac:PostalAddress>
			<cac:PartyLegalEntity>
				<cbc:RegistrationName><![CDATA[AZTECA COMUNICACIONES PERU S.A.C.]]></cbc:RegistrationName>
			</cac:PartyLegalEntity>
		</cac:Party>
	</cac:AccountingCustomerParty>
	<cac:TaxTotal>
		<cbc:TaxAmount currencyID="USD">4026.82</cbc:TaxAmount>
		<cac:TaxSubtotal>
			<cbc:TaxAmount currencyID="USD">4026.82</cbc:TaxAmount>
			<cac:TaxCategory>
				<cac:TaxScheme>
					<cbc:ID>1000</cbc:ID>
					<cbc:Name>IGV</cbc:Name>
					<cbc:TaxTypeCode>VAT</cbc:TaxTypeCode>
				</cac:TaxScheme>
			</cac:TaxCategory>
		</cac:TaxSubtotal>
	</cac:TaxTotal>
	<cac:LegalMonetaryTotal>
		<cbc:PayableAmount currencyID="USD">26398.02</cbc:PayableAmount>
	</cac:LegalMonetaryTotal>
	<cac:InvoiceLine>
		<cbc:ID>1</cbc:ID>
		<cbc:InvoicedQuantity unitCode="NIU">1.000</cbc:InvoicedQuantity>
		<cbc:LineExtensionAmount currencyID="USD">1990.00</cbc:LineExtensionAmount>
		<cac:PricingReference>
			<cac:AlternativeConditionPrice>
				<cbc:PriceAmount currencyID="USD">2348.20</cbc:PriceAmount>
				<cbc:PriceTypeCode>01</cbc:PriceTypeCode>
			</cac:AlternativeConditionPrice>
		</cac:PricingReference>
		<cac:TaxTotal>
			<cbc:TaxAmount currencyID="USD">358.20</cbc:TaxAmount>
			<cac:TaxSubtotal>
				<cbc:TaxableAmount currencyID="USD">0.00</cbc:TaxableAmount>
				<cbc:TaxAmount currencyID="USD">358.20</cbc:TaxAmount>
				<cbc:Percent>18.00</cbc:Percent>
				<cac:TaxCategory>
					<cbc:TaxExemptionReasonCode>10</cbc:TaxExemptionReasonCode>
					<cac:TaxScheme>
						<cbc:ID>1000</cbc:ID>
						<cbc:Name>IGV</cbc:Name>
						<cbc:TaxTypeCode>VAT</cbc:TaxTypeCode>
					</cac:TaxScheme>
				</cac:TaxCategory>
			</cac:TaxSubtotal>
		</cac:TaxTotal>
		<cac:Item>
			<cbc:Description><![CDATA[SERVICIO DE MANTENIMIENTO;; SERVICIO CAMBIO DE FILTRO DE AIRE DE GRUPO ELECTROGENO NODO CAJAMARCA,CELENDIN OCTUBRE]]></cbc:Description>
			<cac:SellersItemIdentification>
				<cbc:ID><![CDATA[8020100031]]></cbc:ID>
			</cac:SellersItemIdentification>
		</cac:Item>
		<cac:Price>
			<cbc:PriceAmount currencyID="USD">1990.00</cbc:PriceAmount>
		</cac:Price>
	</cac:InvoiceLine>
	<cac:InvoiceLine>
		<cbc:ID>2</cbc:ID>
		<cbc:InvoicedQuantity unitCode="NIU">1.000</cbc:InvoicedQuantity>
		<cbc:LineExtensionAmount currencyID="USD">9247.70</cbc:LineExtensionAmount>
		<cac:PricingReference>
			<cac:AlternativeConditionPrice>
				<cbc:PriceAmount currencyID="USD">10912.29</cbc:PriceAmount>
				<cbc:PriceTypeCode>01</cbc:PriceTypeCode>
			</cac:AlternativeConditionPrice>
		</cac:PricingReference>
		<cac:TaxTotal>
			<cbc:TaxAmount currencyID="USD">1664.59</cbc:TaxAmount>
			<cac:TaxSubtotal>
				<cbc:TaxableAmount currencyID="USD">0.00</cbc:TaxableAmount>
				<cbc:TaxAmount currencyID="USD">1664.59</cbc:TaxAmount>
				<cbc:Percent>18.00</cbc:Percent>
				<cac:TaxCategory>
					<cbc:TaxExemptionReasonCode>10</cbc:TaxExemptionReasonCode>
					<cac:TaxScheme>
						<cbc:ID>1000</cbc:ID>
						<cbc:Name>IGV</cbc:Name>
						<cbc:TaxTypeCode>VAT</cbc:TaxTypeCode>
					</cac:TaxScheme>
				</cac:TaxCategory>
			</cac:TaxSubtotal>
		</cac:TaxTotal>
		<cac:Item>
			<cbc:Description><![CDATA[SERVICIO DE MANTENIMIENTO PREVENTIVO;; SERVICIO DE GRUPO ELECTROGENO NODO CAJAMARCA,CELENDIN OCTUBRE]]></cbc:Description>
			<cac:SellersItemIdentification>
				<cbc:ID><![CDATA[8020100002]]></cbc:ID>
			</cac:SellersItemIdentification>
		</cac:Item>
		<cac:Price>
			<cbc:PriceAmount currencyID="USD">9247.70</cbc:PriceAmount>
		</cac:Price>
	</cac:InvoiceLine>
	<cac:InvoiceLine>
		<cbc:ID>3</cbc:ID>
		<cbc:InvoicedQuantity unitCode="NIU">1.000</cbc:InvoicedQuantity>
		<cbc:LineExtensionAmount currencyID="USD">1470.00</cbc:LineExtensionAmount>
		<cac:PricingReference>
			<cac:AlternativeConditionPrice>
				<cbc:PriceAmount currencyID="USD">1734.60</cbc:PriceAmount>
				<cbc:PriceTypeCode>01</cbc:PriceTypeCode>
			</cac:AlternativeConditionPrice>
		</cac:PricingReference>
		<cac:TaxTotal>
			<cbc:TaxAmount currencyID="USD">264.60</cbc:TaxAmount>
			<cac:TaxSubtotal>
				<cbc:TaxableAmount currencyID="USD">0.00</cbc:TaxableAmount>
				<cbc:TaxAmount currencyID="USD">264.60</cbc:TaxAmount>
				<cbc:Percent>18.00</cbc:Percent>
				<cac:TaxCategory>
					<cbc:TaxExemptionReasonCode>10</cbc:TaxExemptionReasonCode>
					<cac:TaxScheme>
						<cbc:ID>1000</cbc:ID>
						<cbc:Name>IGV</cbc:Name>
						<cbc:TaxTypeCode>VAT</cbc:TaxTypeCode>
					</cac:TaxScheme>
				</cac:TaxCategory>
			</cac:TaxSubtotal>
		</cac:TaxTotal>
		<cac:Item>
			<cbc:Description><![CDATA[SERVICIO DE MANTENIMIENTO;; SERVICIO TABLERO DE TRANSFERENCIA DE GRUPO ELECTROGENO NODO CAJAMARCA,CELENDIN,CHOTA  OCTUBRE]]></cbc:Description>
			<cac:SellersItemIdentification>
				<cbc:ID><![CDATA[8020100031]]></cbc:ID>
			</cac:SellersItemIdentification>
		</cac:Item>
		<cac:Price>
			<cbc:PriceAmount currencyID="USD">1470.00</cbc:PriceAmount>
		</cac:Price>
	</cac:InvoiceLine>
	<cac:InvoiceLine>
		<cbc:ID>4</cbc:ID>
		<cbc:InvoicedQuantity unitCode="NIU">1.000</cbc:InvoicedQuantity>
		<cbc:LineExtensionAmount currencyID="USD">6120.00</cbc:LineExtensionAmount>
		<cac:PricingReference>
			<cac:AlternativeConditionPrice>
				<cbc:PriceAmount currencyID="USD">7221.60</cbc:PriceAmount>
				<cbc:PriceTypeCode>01</cbc:PriceTypeCode>
			</cac:AlternativeConditionPrice>
		</cac:PricingReference>
		<cac:TaxTotal>
			<cbc:TaxAmount currencyID="USD">1101.60</cbc:TaxAmount>
			<cac:TaxSubtotal>
				<cbc:TaxableAmount currencyID="USD">0.00</cbc:TaxableAmount>
				<cbc:TaxAmount currencyID="USD">1101.60</cbc:TaxAmount>
				<cbc:Percent>18.00</cbc:Percent>
				<cac:TaxCategory>
					<cbc:TaxExemptionReasonCode>10</cbc:TaxExemptionReasonCode>
					<cac:TaxScheme>
						<cbc:ID>1000</cbc:ID>
						<cbc:Name>IGV</cbc:Name>
						<cbc:TaxTypeCode>VAT</cbc:TaxTypeCode>
					</cac:TaxScheme>
				</cac:TaxCategory>
			</cac:TaxSubtotal>
		</cac:TaxTotal>
		<cac:Item>
			<cbc:Description><![CDATA[SERVICIO DE MANTENIMIENTO PREVENTIVO;; SERVICIO DE PRUEBAS DE CARGA DE GRUPO ELECTROGENO NODO,CHOTA, CUMBIL OCTUBRE]]></cbc:Description>
			<cac:SellersItemIdentification>
				<cbc:ID><![CDATA[8020100002]]></cbc:ID>
			</cac:SellersItemIdentification>
		</cac:Item>
		<cac:Price>
			<cbc:PriceAmount currencyID="USD">6120.00</cbc:PriceAmount>
		</cac:Price>
	</cac:InvoiceLine>
	<cac:InvoiceLine>
		<cbc:ID>5</cbc:ID>
		<cbc:InvoicedQuantity unitCode="NIU">1.000</cbc:InvoicedQuantity>
		<cbc:LineExtensionAmount currencyID="USD">425.00</cbc:LineExtensionAmount>
		<cac:PricingReference>
			<cac:AlternativeConditionPrice>
				<cbc:PriceAmount currencyID="USD">501.50</cbc:PriceAmount>
				<cbc:PriceTypeCode>01</cbc:PriceTypeCode>
			</cac:AlternativeConditionPrice>
		</cac:PricingReference>
		<cac:TaxTotal>
			<cbc:TaxAmount currencyID="USD">76.50</cbc:TaxAmount>
			<cac:TaxSubtotal>
				<cbc:TaxableAmount currencyID="USD">0.00</cbc:TaxableAmount>
				<cbc:TaxAmount currencyID="USD">76.50</cbc:TaxAmount>
				<cbc:Percent>18.00</cbc:Percent>
				<cac:TaxCategory>
					<cbc:TaxExemptionReasonCode>10</cbc:TaxExemptionReasonCode>
					<cac:TaxScheme>
						<cbc:ID>1000</cbc:ID>
						<cbc:Name>IGV</cbc:Name>
						<cbc:TaxTypeCode>VAT</cbc:TaxTypeCode>
					</cac:TaxScheme>
				</cac:TaxCategory>
			</cac:TaxSubtotal>
		</cac:TaxTotal>
		<cac:Item>
			<cbc:Description><![CDATA[SERVICIO DE MANTENIMIENTO;; SERVICIO CAMBIO DE FILTRO DE AIRE DE GRUPO ELECTROGENO NODO CHACHAPOYAS, MENDOZA, NOVIEMBRE]]></cbc:Description>
			<cac:SellersItemIdentification>
				<cbc:ID><![CDATA[8020100031]]></cbc:ID>
			</cac:SellersItemIdentification>
		</cac:Item>
		<cac:Price>
			<cbc:PriceAmount currencyID="USD">425.00</cbc:PriceAmount>
		</cac:Price>
	</cac:InvoiceLine>
	<cac:InvoiceLine>
		<cbc:ID>6</cbc:ID>
		<cbc:InvoicedQuantity unitCode="NIU">1.000</cbc:InvoicedQuantity>
		<cbc:LineExtensionAmount currencyID="USD">3118.50</cbc:LineExtensionAmount>
		<cac:PricingReference>
			<cac:AlternativeConditionPrice>
				<cbc:PriceAmount currencyID="USD">3679.83</cbc:PriceAmount>
				<cbc:PriceTypeCode>01</cbc:PriceTypeCode>
			</cac:AlternativeConditionPrice>
		</cac:PricingReference>
		<cac:TaxTotal>
			<cbc:TaxAmount currencyID="USD">561.33</cbc:TaxAmount>
			<cac:TaxSubtotal>
				<cbc:TaxableAmount currencyID="USD">0.00</cbc:TaxableAmount>
				<cbc:TaxAmount currencyID="USD">561.33</cbc:TaxAmount>
				<cbc:Percent>18.00</cbc:Percent>
				<cac:TaxCategory>
					<cbc:TaxExemptionReasonCode>10</cbc:TaxExemptionReasonCode>
					<cac:TaxScheme>
						<cbc:ID>1000</cbc:ID>
						<cbc:Name>IGV</cbc:Name>
						<cbc:TaxTypeCode>VAT</cbc:TaxTypeCode>
					</cac:TaxScheme>
				</cac:TaxCategory>
			</cac:TaxSubtotal>
		</cac:TaxTotal>
		<cac:Item>
			<cbc:Description><![CDATA[SERVICIO DE MANTENIMIENTO PREVENTIVO;; GRUPO ELECTROGENO NODO CHACHAPOYAS, MENDOZA, NOVIEMBRE]]></cbc:Description>
			<cac:SellersItemIdentification>
				<cbc:ID><![CDATA[8020100002]]></cbc:ID>
			</cac:SellersItemIdentification>
		</cac:Item>
		<cac:Price>
			<cbc:PriceAmount currencyID="USD">3118.50</cbc:PriceAmount>
		</cac:Price>
	</cac:InvoiceLine>
</Invoice>